[
    {
        "key": "dbln",
        "value": "%7B%2261572236771681%22%3A%227AKGMDtX%22%7D",
        "domain": "facebook.com",
        "path": "/login/device-based/",
        "hostOnly": false,
        "creation": "2025-09-18T15:00:09.631Z",
        "lastAccessed": "2025-09-18T15:00:09.631Z"
    },
    {
        "key": "datr",
        "value": "Zh3MaPv0qcGMmgsBpF23d3xy",
        "domain": "facebook.com",
        "path": "/",
        "hostOnly": false,
        "creation": "2025-09-18T15:00:09.631Z",
        "lastAccessed": "2025-09-18T15:00:09.631Z"
    },
    {
        "key": "sb",
        "value": "Zh3MaJThoYx2ZgZqiGcSIErO",
        "domain": "facebook.com",
        "path": "/",
        "hostOnly": false,
        "creation": "2025-09-18T15:00:09.631Z",
        "lastAccessed": "2025-09-18T15:00:09.631Z"
    },
    {
        "key": "m_pixel_ratio",
        "value": "2",
        "domain": "facebook.com",
        "path": "/",
        "hostOnly": false,
        "creation": "2025-09-18T15:00:09.631Z",
        "lastAccessed": "2025-09-18T15:00:09.631Z"
    },
    {
        "key": "ps_l",
        "value": "1",
        "domain": "facebook.com",
        "path": "/",
        "hostOnly": false,
        "creation": "2025-09-18T15:00:09.631Z",
        "lastAccessed": "2025-09-18T15:00:09.631Z"
    },
    {
        "key": "ps_n",
        "value": "1",
        "domain": "facebook.com",
        "path": "/",
        "hostOnly": false,
        "creation": "2025-09-18T15:00:09.631Z",
        "lastAccessed": "2025-09-18T15:00:09.631Z"
    },
    {
        "key": "c_user",
        "value": "61572236771681",
        "domain": "facebook.com",
        "path": "/",
        "hostOnly": false,
        "creation": "2025-09-18T15:00:09.631Z",
        "lastAccessed": "2025-09-18T15:00:09.631Z"
    },
    {
        "key": "xs",
        "value": "17%3Ar6vvpjflJ5-Plw%3A2%3A1758207481%3A-1%3A-1",
        "domain": "facebook.com",
        "path": "/",
        "hostOnly": false,
        "creation": "2025-09-18T15:00:09.631Z",
        "lastAccessed": "2025-09-18T15:00:09.631Z"
    },
    {
        "key": "locale",
        "value": "en_US",
        "domain": "facebook.com",
        "path": "/",
        "hostOnly": false,
        "creation": "2025-09-18T15:00:09.631Z",
        "lastAccessed": "2025-09-18T15:00:09.631Z"
    },
    {
        "key": "wl_cbv",
        "value": "v2%3Bclient_version%3A2926%3Btimestamp%3A1758207489",
        "domain": "facebook.com",
        "path": "/",
        "hostOnly": false,
        "creation": "2025-09-18T15:00:09.631Z",
        "lastAccessed": "2025-09-18T15:00:09.631Z"
    },
    {
        "key": "fbl_st",
        "value": "100634269%3BT%3A29303456",
        "domain": "facebook.com",
        "path": "/",
        "hostOnly": false,
        "creation": "2025-09-18T15:00:09.631Z",
        "lastAccessed": "2025-09-18T15:00:09.631Z"
    },
    {
        "key": "vpd",
        "value": "v1%3B566x360x2",
        "domain": "facebook.com",
        "path": "/",
        "hostOnly": false,
        "creation": "2025-09-18T15:00:09.632Z",
        "lastAccessed": "2025-09-18T15:00:09.632Z"
    },
    {
        "key": "wd",
        "value": "980x1541",
        "domain": "facebook.com",
        "path": "/",
        "hostOnly": false,
        "creation": "2025-09-18T15:00:09.632Z",
        "lastAccessed": "2025-09-18T15:00:09.632Z"
    },
    {
        "key": "dpr",
        "value": "2",
        "domain": "facebook.com",
        "path": "/",
        "hostOnly": false,
        "creation": "2025-09-18T15:00:09.632Z",
        "lastAccessed": "2025-09-18T15:00:09.632Z"
    },
    {
        "key": "i_user",
        "value": "61574849241432",
        "domain": "facebook.com",
        "path": "/",
        "hostOnly": false,
        "creation": "2025-09-18T15:00:09.632Z",
        "lastAccessed": "2025-09-18T15:00:09.632Z"
    },
    {
        "key": "fr",
        "value": "0KaovQKQmOTgZWsoH.AWcjF0tC-zUtZuUi0caR5bP8zpGa20UhZWhy4wnCNx3emC2x5po.BozB1m..AAA.0.0.BozB43.AWdUxjXGFJwrnfJNUl7O1BFxA_0",
        "domain": "facebook.com",
        "path": "/",
        "hostOnly": false,
        "creation": "2025-09-18T15:00:09.632Z",
        "lastAccessed": "2025-09-18T15:00:09.632Z"
    },
    {
        "key": "presence",
        "value": "C%7B%22t3%22%3A%5B%5D%2C%22utc3%22%3A1758207470182%2C%22v%22%3A1%7D",
        "domain": "facebook.com",
        "path": "/",
        "hostOnly": false,
        "creation": "2025-09-18T15:00:09.632Z",
        "lastAccessed": "2025-09-18T15:00:09.632Z"
    }
        ]
